cocotbext/pcie/core/__init__.py
cocotbext/pcie/core/bridge.py
cocotbext/pcie/core/device.py
cocotbext/pcie/core/dllp.py
cocotbext/pcie/core/endpoint.py
cocotbext/pcie/core/function.py
cocotbext/pcie/core/msi.py
cocotbext/pcie/core/pci.py
cocotbext/pcie/core/port.py
cocotbext/pcie/core/rc.py
cocotbext/pcie/core/region.py
cocotbext/pcie/core/switch.py
cocotbext/pcie/core/tlp.py
cocotbext/pcie/core/utils.py
cocotbext/pcie/core/version.py
cocotbext/pcie/core/caps/__init__.py
cocotbext/pcie/core/caps/aer.py
cocotbext/pcie/core/caps/common.py
cocotbext/pcie/core/caps/msi.py
cocotbext/pcie/core/caps/pcie.py
cocotbext/pcie/core/caps/pm.py
cocotbext/pcie/intel/ptile/__init__.py
cocotbext/pcie/intel/ptile/interface.py
cocotbext/pcie/intel/ptile/ptile_model.py
cocotbext/pcie/intel/s10/__init__.py
cocotbext/pcie/intel/s10/interface.py
cocotbext/pcie/intel/s10/s10_model.py
cocotbext/pcie/xilinx/us/__init__.py
cocotbext/pcie/xilinx/us/interface.py
cocotbext/pcie/xilinx/us/tlp.py
cocotbext/pcie/xilinx/us/us_model.py
cocotbext/pcie/xilinx/us/usp_model.py
cocotbext_pcie-0.2.14.dist-info/LICENSE
cocotbext_pcie-0.2.14.dist-info/METADATA
cocotbext_pcie-0.2.14.dist-info/WHEEL
cocotbext_pcie-0.2.14.dist-info/top_level.txt
cocotbext_pcie-0.2.14.dist-info/RECORD
