Metadata-Version: 2.1
Name: cocotbext-pcie
Version: 0.2.14
Summary: PCI express simulation framework for cocotb
Home-page: https://github.com/alexforencich/cocotbext-pcie
Download-URL: https://github.com/alexforencich/cocotbext-pcie/tarball/master
Author: Alex Forencich
Author-email: alex@alexforencich.com
License: MIT
Project-URL: Bug Tracker, https://github.com/alexforencich/cocotbext-pcie/issues
Project-URL: Source Code, https://github.com/alexforencich/cocotbext-pcie
Keywords: pcie,cocotb
Platform: any
Classifier: Development Status :: 3 - Alpha
Classifier: Framework :: cocotb
Classifier: License :: OSI Approved :: MIT License
Classifier: Operating System :: OS Independent
Classifier: Programming Language :: Python :: 3
Classifier: Topic :: Scientific/Engineering :: Electronic Design Automation (EDA)
Requires-Python: >=3.6
License-File: LICENSE
Requires-Dist: cocotb (>=1.6.0)
Requires-Dist: cocotbext-axi (>=0.1.16)
Provides-Extra: test
Requires-Dist: pytest ; extra == 'test'
Requires-Dist: cocotb-test ; extra == 'test'
